odoo/addons/stock_production_lot_multi_company/README.rst
odoo/addons/stock_production_lot_multi_company/__init__.py
odoo/addons/stock_production_lot_multi_company/__manifest__.py
odoo/addons/stock_production_lot_multi_company/i18n/de.po
odoo/addons/stock_production_lot_multi_company/i18n/es.po
odoo/addons/stock_production_lot_multi_company/i18n/hr.po
odoo/addons/stock_production_lot_multi_company/i18n/nl_NL.po
odoo/addons/stock_production_lot_multi_company/i18n/pt.po
odoo/addons/stock_production_lot_multi_company/i18n/pt_BR.po
odoo/addons/stock_production_lot_multi_company/i18n/sl.po
odoo/addons/stock_production_lot_multi_company/i18n/stock_production_lot_multi_company.pot
odoo/addons/stock_production_lot_multi_company/models/__init__.py
odoo/addons/stock_production_lot_multi_company/models/stock_production_lot.py
odoo/addons/stock_production_lot_multi_company/security/stock_production_lot_security.xml
odoo/addons/stock_production_lot_multi_company/static/description/icon.png
odoo/addons/stock_production_lot_multi_company/tests/__init__.py
odoo/addons/stock_production_lot_multi_company/tests/test_stock_production_lot_multi_company.py
odoo/addons/stock_production_lot_multi_company/views/stock_production_lot_view.xml
odoo11_addon_stock_production_lot_multi_company-11.0.1.1.0.99.dev2.dist-info/METADATA
odoo11_addon_stock_production_lot_multi_company-11.0.1.1.0.99.dev2.dist-info/RECORD
odoo11_addon_stock_production_lot_multi_company-11.0.1.1.0.99.dev2.dist-info/WHEEL
odoo11_addon_stock_production_lot_multi_company-11.0.1.1.0.99.dev2.dist-info/top_level.txt
